{"name": "E3", "fps": 12, "loop": false, "frames": [{"sprite": "sp_027439b1.png", "duration_ms": 83}, {"sprite": "sp_2db9c2f7.png", "duration_ms": 83}, {"sprite": "sp_b143aa1b.png", "duration_ms": 83}, {"sprite": "sp_9b2d8dc0.png", "duration_ms": 83}, {"sprite": "sp_a0cd5f91.png", "duration_ms": 83}, {"sprite": "sp_64e6d301.png", "duration_ms": 83}, {"sprite": "sp_542a418e.png", "duration_ms": 83}, {"sprite": "sp_16a3768f.png", "duration_ms": 83}, {"sprite": "sp_226e2943.png", "duration_ms": 83}, {"sprite": "sp_c86f21cb.png", "duration_ms": 83}, {"sprite": "sp_f65ad445.png", "duration_ms": 83}, {"sprite": "sp_3573b465.png", "duration_ms": 83}, {"sprite": "sp_ec04e052.png", "duration_ms": 83}, {"sprite": "sp_055db1a2.png", "duration_ms": 83}, {"sprite": "sp_ee21600d.png", "duration_ms": 83}, {"sprite": "sp_bb760698.png", "duration_ms": 83}, {"sprite": "sp_728ddfd0.png", "duration_ms": 83}, {"sprite": "sp_9880f8c4.png", "duration_ms": 83}, {"sprite": "sp_4aecff47.png", "duration_ms": 83}, {"sprite": "sp_b1f1a7ef.png", "duration_ms": 83}, {"sprite": "sp_b2907fb6.png", "duration_ms": 83}, {"sprite": "sp_6ba3300b.png", "duration_ms": 83}, {"sprite": "sp_2b215835.png", "duration_ms": 83}, {"sprite": "sp_5b36e39a.png", "duration_ms": 83}, {"sprite": "sp_fe2562a0.png", "duration_ms": 83}, {"sprite": "sp_44af4b78.png", "duration_ms": 83}, {"sprite": "sp_76826018.png", "duration_ms": 83}, {"sprite": "sp_8a6cdff8.png", "duration_ms": 83}, {"sprite": "sp_bcbc4c39.png", "duration_ms": 83}, {"sprite": "sp_c4312085.png", "duration_ms": 83}, {"sprite": "sp_ad2f3b21.png", "duration_ms": 83}, {"sprite": "sp_54ec3a39.png", "duration_ms": 83}, {"sprite": "sp_571bcb8a.png", "duration_ms": 83}, {"sprite": "sp_4715201f.png", "duration_ms": 83}, {"sprite": "sp_b59f1933.png", "duration_ms": 83}, {"sprite": "sp_d54a8d9f.png", "duration_ms": 83}, {"sprite": "sp_d977fb82.png", "duration_ms": 83}, {"sprite": "sp_c3489b05.png", "duration_ms": 83}, {"sprite": "sp_1badf3d5.png", "duration_ms": 83}, {"sprite": "sp_fbece9b2.png", "duration_ms": 83}, {"sprite": "sp_10854f84.png", "duration_ms": 83}, {"sprite": "sp_2eb332ad.png", "duration_ms": 83}, {"sprite": "sp_dad5227d.png", "duration_ms": 83}, {"sprite": "sp_2db765d0.png", "duration_ms": 83}, {"sprite": "sp_61e17dc7.png", "duration_ms": 83}, {"sprite": "sp_2fbf419e.png", "duration_ms": 83}, {"sprite": "sp_4d277204.png", "duration_ms": 83}, {"sprite": "sp_5893abff.png", "duration_ms": 83}, {"sprite": "sp_9ce55cbc.png", "duration_ms": 83}, {"sprite": "sp_3cbe4af5.png", "duration_ms": 83}, {"sprite": "sp_c9c8d0d4.png", "duration_ms": 83}, {"sprite": "sp_47f5ae8d.png", "duration_ms": 83}, {"sprite": "sp_27d8ddad.png", "duration_ms": 83}, {"sprite": "sp_b495e533.png", "duration_ms": 83}]}