{"name": "H3", "fps": 12, "loop": false, "frames": [{"sprite": "sp_c5fafa07.png", "duration_ms": 83}, {"sprite": "sp_286b4fc2.png", "duration_ms": 83}, {"sprite": "sp_53f40240.png", "duration_ms": 83}, {"sprite": "sp_78bff83b.png", "duration_ms": 83}, {"sprite": "sp_90c1beaf.png", "duration_ms": 83}, {"sprite": "sp_82d04341.png", "duration_ms": 83}, {"sprite": "sp_9dfd5869.png", "duration_ms": 83}, {"sprite": "sp_e99c2f69.png", "duration_ms": 83}, {"sprite": "sp_d122f7f8.png", "duration_ms": 83}, {"sprite": "sp_70789aed.png", "duration_ms": 83}, {"sprite": "sp_1e9f17d5.png", "duration_ms": 83}, {"sprite": "sp_5e072306.png", "duration_ms": 83}, {"sprite": "sp_670b9905.png", "duration_ms": 83}, {"sprite": "sp_673a3516.png", "duration_ms": 83}, {"sprite": "sp_50a18888.png", "duration_ms": 83}, {"sprite": "sp_9607b98f.png", "duration_ms": 83}, {"sprite": "sp_da330e2f.png", "duration_ms": 83}, {"sprite": "sp_3018106b.png", "duration_ms": 83}, {"sprite": "sp_c63952bc.png", "duration_ms": 83}, {"sprite": "sp_c9ab55d7.png", "duration_ms": 83}, {"sprite": "sp_01a3a404.png", "duration_ms": 83}, {"sprite": "sp_4d9b2b89.png", "duration_ms": 83}, {"sprite": "sp_1893e1a7.png", "duration_ms": 83}, {"sprite": "sp_b22c6183.png", "duration_ms": 83}, {"sprite": "sp_2f48bea7.png", "duration_ms": 83}, {"sprite": "sp_467fae81.png", "duration_ms": 83}, {"sprite": "sp_58de6b23.png", "duration_ms": 83}, {"sprite": "sp_c5bdd24d.png", "duration_ms": 83}, {"sprite": "sp_5980024b.png", "duration_ms": 83}, {"sprite": "sp_6568b7b3.png", "duration_ms": 83}, {"sprite": "sp_46e453fb.png", "duration_ms": 83}, {"sprite": "sp_bd582ed5.png", "duration_ms": 83}, {"sprite": "sp_5ac64cee.png", "duration_ms": 83}, {"sprite": "sp_34f8ef86.png", "duration_ms": 83}, {"sprite": "sp_1f2bd859.png", "duration_ms": 83}, {"sprite": "sp_628d19aa.png", "duration_ms": 83}, {"sprite": "sp_e1fb66f4.png", "duration_ms": 83}, {"sprite": "sp_b8138910.png", "duration_ms": 83}, {"sprite": "sp_c4c22511.png", "duration_ms": 83}, {"sprite": "sp_ec68a3e5.png", "duration_ms": 83}, {"sprite": "sp_fbb53b92.png", "duration_ms": 83}, {"sprite": "sp_17f02c02.png", "duration_ms": 83}, {"sprite": "sp_3c609fa5.png", "duration_ms": 83}, {"sprite": "sp_682f7190.png", "duration_ms": 83}, {"sprite": "sp_ae227974.png", "duration_ms": 83}, {"sprite": "sp_a0d7c841.png", "duration_ms": 83}, {"sprite": "sp_40868e45.png", "duration_ms": 83}, {"sprite": "sp_7aa071a3.png", "duration_ms": 83}, {"sprite": "sp_f9f1ce87.png", "duration_ms": 83}, {"sprite": "sp_27385d35.png", "duration_ms": 83}, {"sprite": "sp_56b420bb.png", "duration_ms": 83}, {"sprite": "sp_a546c4c1.png", "duration_ms": 83}, {"sprite": "sp_7750fdc9.png", "duration_ms": 83}, {"sprite": "sp_6b533918.png", "duration_ms": 83}, {"sprite": "sp_afcb63e0.png", "duration_ms": 83}]}